pycmdparse/__init__.py
pycmdparse/abstract_opt.py
pycmdparse/bool_opt.py
pycmdparse/class_property.py
pycmdparse/cmdline.py
pycmdparse/cmdline_exception.py
pycmdparse/datatype_enum.py
pycmdparse/multitype_enum.py
pycmdparse/opt_acceptresult_enum.py
pycmdparse/opt_category.py
pycmdparse/opt_factory.py
pycmdparse/param_opt.py
pycmdparse/parseresult_enum.py
pycmdparse/positional_params.py
pycmdparse/showinfo.py
pycmdparse/splitter.py
pycmdparse/stack.py
pycmdparse/usage_example.py
pycmdparse/util.py
pycmdparse-1.0.0.dist-info/LICENSE
pycmdparse-1.0.0.dist-info/METADATA
pycmdparse-1.0.0.dist-info/WHEEL
pycmdparse-1.0.0.dist-info/top_level.txt
pycmdparse-1.0.0.dist-info/RECORD
