Metadata-Version: 2.1
Name: pycmdparse
Version: 1.0.0
Summary: A Python command line arg parser, and usage instructions generator
Home-page: https://github.com/aceeric/pycmdparse
Author: Eric Ace
Author-email: ericace@protonmail.com
License: Public Domain
Keywords: arg argument parse command line usage instructions console utility
Platform: UNKNOWN
Classifier: Development Status :: 5 - Production/Stable
Classifier: Intended Audience :: Developers
Classifier: License :: Public Domain
Classifier: Operating System :: OS Independent
Classifier: Environment :: Console
Classifier: Programming Language :: Python
Classifier: Programming Language :: Python :: 3.6
Classifier: Programming Language :: Python :: Implementation :: PyPy
Classifier: Topic :: Software Development :: Libraries :: Python Modules
Classifier: Topic :: Text Processing :: Markup
Requires-Python: ~=3.6
Requires-Dist: PyYAML (==5.1b3)
